Workbook
Name lookup21: #REF!

Sheet Summary.Confidential
A1: Procurement Advisors - Benchmarking Summary
A2: Customer | B2: Molnlycie
A3: Date Range | B3: 01/21-12/21
A5: Savings vs. Current | B5: Paid Price | C5: Current Price | D5: PA Price | E5: Savings $ | F5: Savings % | G5: Comments
A6: =_xlfn.CONCAT(B2," current price against PA price") -> Molnlycie current price against PA price | B6: =C22 -> 30767.19 | C6: =SUM(ItemDetail.Confidential!$V:$V) -> 33074.729 | D6: =SUM(ItemDetail.Confidential!$R:$R) -> 27876.359 | E6: =C6-D6 -> 5198.3697 | F6: =E6/C6 -> 0.15717044 | G6: Exact SKU benchmarking
A8: No. of SKUs | B8: Negative | C8: Same | D8: 0-10% | E8: 10-20% | F8: 20-30% | G8: 30+% | H8: Total
A9: Total SKUs | B9: =COUNTIF(ItemDetail.Confidential!$Z:$Z,B8) -> 7 | C9: =COUNTIF(ItemDetail.Confidential!$Z:$Z,C8) -> 0 | D9: =COUNTIF(ItemDetail.Confidential!$Z:$Z,D8) -> 19 | E9: =COUNTIF(ItemDetail.Confidential!$Z:$Z,E8) -> 23 | F9: =COUNTIF(ItemDetail.Confidential!$Z:$Z,F8) -> 6 | G9: =COUNTIF(ItemDetail.Confidential!$Z:$Z,G8) -> 12 | H9: =SUM(B9:G9) -> 67
A11: $ Spend | B11: Negative | C11: Same | D11: 0-10% | E11: 10-20% | F11: 20-30% | G11: 30+% | H11: Total
A12: =_xlfn.CONCAT("Fisher-",B2) -> Fisher-Molnlycie | B12: =SUMIF(ItemDetail.Confidential!$Z:$Z,B11,ItemDetail.Confidential!$V:$V) -> 817.4945 | C12: =SUMIF(ItemDetail.Confidential!$Z:$Z,C11,ItemDetail.Confidential!$V:$V) -> 0 | D12: =SUMIF(ItemDetail.Confidential!$Z:$Z,D11,ItemDetail.Confidential!$V:$V) -> 6898.5653 | E12: =SUMIF(ItemDetail.Confidential!$Z:$Z,E11,ItemDetail.Confidential!$V:$V) -> 16972.853 | F12: =SUMIF(ItemDetail.Confidential!$Z:$Z,F11,ItemDetail.Confidential!$V:$V) -> 6248.502 | G12: =SUMIF(ItemDetail.Confidential!$Z:$Z,G11,ItemDetail.Confidential!$V:$V) -> 2137.315 | H12: =SUM(B12:G12) -> 33074.729
A13: Fisher-PA | B13: =SUMIF(ItemDetail.Confidential!$Z:$Z,B11,ItemDetail.Confidential!$R:$R) -> 850.52 | C13: =SUMIF(ItemDetail.Confidential!$Z:$Z,C11,ItemDetail.Confidential!$R:$R) -> 0 | D13: =SUMIF(ItemDetail.Confidential!$Z:$Z,D11,ItemDetail.Confidential!$R:$R) -> 6523.5 | E13: =SUMIF(ItemDetail.Confidential!$Z:$Z,E11,ItemDetail.Confidential!$R:$R) -> 14890.629 | F13: =SUMIF(ItemDetail.Confidential!$Z:$Z,F11,ItemDetail.Confidential!$R:$R) -> 4672.11 | G13: =SUMIF(ItemDetail.Confidential!$Z:$Z,G11,ItemDetail.Confidential!$R:$R) -> 926.31 | H13: =SUM(B13:G13) -> 27863.07
A14: SKU Level Savings | B14: =B12-B13 -> -33.0255 | C14: =C12-C13 -> 0 | D14: =D12-D13 -> 375.06525 | E14: =E12-E13 -> 2082.223 | F14: =F12-F13 -> 1576.392 | G14: =G12-G13 -> 1211.005 | H14: =H12-H13 -> 5211.6598
B15: =B12/H12 -> 0.024716589 | C15: =C12/H12 -> 0
A16: CSPL breakdown | B16: SKUs | C16: % | D16: $ | E16: PA $ | F16: Savings % | G16: Savings $ | H16: Comments
A17: CSPL Skus | B17: =COUNTIF(ItemDetail.Confidential!$T:$T,"Y") -> 15 | C17: =D17/D19 -> 0.077727605 | D17: =SUMIF(ItemDetail.Confidential!$T:$T,"Y",ItemDetail.Confidential!$V:$V) -> 2570.8195 | E17: =SUMIF(ItemDetail.Confidential!$T:$T,"Y",ItemDetail.Confidential!$R:$R) -> 1611.56 | F17: =1-E17/D17 -> 0.37313374 | G17: =D17-E17 -> 959.2595 | H17: Deeply discounted SKU List
A18: Non-CSPL Skus | B18: =COUNTIF(ItemDetail.Confidential!$T:$T,"N") -> 53 | C18: =D18/D19 -> 0.92227239 | D18: =SUMIF(ItemDetail.Confidential!$T:$T,"N",ItemDetail.Confidential!$V:$V) -> 30503.91 | E18: =SUMIF(ItemDetail.Confidential!$T:$T,"N",ItemDetail.Confidential!$R:$R) -> 26264.799 | F18: =1-E18/D18 -> 0.13896941 | G18: =D18-E18 -> 4239.1102 | H18: Category Discounts (15-50%) or Spot Discounts of atleast 10%
A19: Total | B19: =SUM(B17:B18) -> 68 | C19: =SUM(C17:C18) -> 1 | D19: =SUM(D17:D18) -> 33074.729 | E19: =SUM(E17:E18) -> 27876.359 | F19: =1-E19/D19 -> 0.15717044 | G19: =SUM(G17:G18) -> 5198.3697
A21: Savings vs. Paid | B21: Total Spend Provided | C21: Benchmarked Spend | D21: Benchmarked % of Total | E21: PA Pricing | F21: Savings $ | G21: Savings | H21: Comments
A22: Fisher | B22: =SUM(ItemDetail.Confidential!$L:$L)+SUM(Excluded.Confidential!$L:$L) -> 30767.19 | C22: =SUMIF(ItemDetail.Confidential!$S:$S,">-9e100",ItemDetail.Confidential!$L:$L) -> 30767.19 | D22: =C22/B22 -> 1 | E22: =SUMIF(ItemDetail.Confidential!$S:$S,">-9e100",ItemDetail.Confidential!$R:$R) -> 27876.359 | F22: =C22-E22 -> 2890.8305 | G22: =SUM(1-(E22/C22)) -> 0.093958223 | H22: Exact SKU benchmarking
A23: Overall Savings | F23: =SUM(F22:F22) -> 2890.8305 | G23: =F23/C22 -> 0.093958223
A25: Other savings opportunities:
A26: Free Freight Benefit
A27: Paid freight Prior 12 months | B27: 0
A28: PA freight charges | B28: 0
A29: Annual Freight Savings Benefit | B29: =B27-B28 -> 0 | C29: estimate
A31: Net 60 benefit
A32: Annual rate of return (estimated) | B32: 0.08
A33: Current payment terms (largest act, in days) | B33: 30
A34: PA payment terms (in days) | B34: 60
A35: Payment Term benefit adjustment | B35: =B32/365*(B34-B33) -> 0.0065753425
A36: R12 Spend | B36: =B22 -> 30767.19
A37: Preferred terms estimate | B37: =B36*B35 -> 202.30481 | C37: estimate
A40: Note:
A41: (1) Total spend is data provided by Fisher
A42: (2) Benchmarked all SKUs except sourced items
A43: (3) Used company purchase history to compare against PA current price
A44: (4) Savings do not reflect (a) volume and manufacturer rebates, (b) CSPL alternatives and future CSPL adds
A45: (5) Benchmark pricing valid for 60 days
A46: (6) "Other Savings" numbers are projections based on historical spend and current agreements, actual numbers and percentages will change based of future spend patterns

Sheet Loc.Summ.Confidential
A1: Location Summary
A2: # | B2: Location Name | C2: # SKUs | D2: Total Paid | E2: PA Ext. Price | F2: Savings $ | G2: Savings %
A3: 1 | B3: BRUNSWICK | C3: =COUNTIF(ItemDetail.Confidential!$A:$A,B3) -> 20 | D3: =SUMIF(ItemDetail.Confidential!$A:$A,B3,ItemDetail.Confidential!$V:$V) -> 6423.4797 | E3: =SUMIF(ItemDetail.Confidential!$A:$A,B3,ItemDetail.Confidential!$R:$R) -> 5579.68 | F3: =D3-E3 -> 843.79975 | G3: =IFERROR(F3/D3,"") -> 0.13136178
A4: =A3+1 -> 2 | B4: WISCASSET | C4: =COUNTIF(ItemDetail.Confidential!$A:$A,B4) -> 48 | D4: =SUMIF(ItemDetail.Confidential!$A:$A,B4,ItemDetail.Confidential!$V:$V) -> 26651.249 | E4: =SUMIF(ItemDetail.Confidential!$A:$A,B4,ItemDetail.Confidential!$R:$R) -> 22296.679 | F4: =D4-E4 -> 4354.57 | G4: =IFERROR(F4/D4,"") -> 0.16339084
B5: Total | C5: =SUM(C3:C4) -> 68 | D5: =SUM(D3:D4) -> 33074.729 | E5: =SUM(E3:E4) -> 27876.359 | F5: =D5-E5 -> 5198.3698 | G5: =IFERROR(F5/D5,"") -> 0.15717044

Sheet Segment.Confidential
A1: Segment Breakdown
A2: Segment | B2: # SKUs | C2: Total Spend | D2: PA Ext Price | E2: % of Total | F2: Savings $ | G2: Saving %
A3: Analytical Chemicals | B3: =COUNTIF(ItemDetail.Confidential!$J:$J,A3) -> 4 | C3: =SUMIF(ItemDetail.Confidential!$J:$J,A3,ItemDetail.Confidential!$V:$V) -> 10748.216 | D3: =SUMIF(ItemDetail.Confidential!$J:$J,A3,ItemDetail.Confidential!$R:$R) -> 8827.235 | E3: =C3/$C$25 -> 0.3249676 | F3: =C3-D3 -> 1920.9805 | G3: =IFERROR(F3/C3,0) -> 0.17872553
A4: Buffers | B4: =COUNTIF(ItemDetail.Confidential!$J:$J,A4) -> 3 | C4: =SUMIF(ItemDetail.Confidential!$J:$J,A4,ItemDetail.Confidential!$V:$V) -> 140.653 | D4: =SUMIF(ItemDetail.Confidential!$J:$J,A4,ItemDetail.Confidential!$R:$R) -> 19.49 | E4: =C4/$C$25 -> 0.0042525821 | F4: =C4-D4 -> 121.163 | G4: =IFERROR(F4/C4,0) -> 0.86143203
A5: Chromatography Consumables | B5: =COUNTIF(ItemDetail.Confidential!$J:$J,A5) -> 2 | C5: =SUMIF(ItemDetail.Confidential!$J:$J,A5,ItemDetail.Confidential!$V:$V) -> 264.4715 | D5: =SUMIF(ItemDetail.Confidential!$J:$J,A5,ItemDetail.Confidential!$R:$R) -> 250.7 | E5: =C5/$C$25 -> 0.0079961803 | F5: =C5-D5 -> 13.7715 | G5: =IFERROR(F5/C5,0) -> 0.052071773
A6: Controlled Environments | B6: =COUNTIF(ItemDetail.Confidential!$J:$J,A6) -> 4 | C6: =SUMIF(ItemDetail.Confidential!$J:$J,A6,ItemDetail.Confidential!$V:$V) -> 969.23075 | D6: =SUMIF(ItemDetail.Confidential!$J:$J,A6,ItemDetail.Confidential!$R:$R) -> 853.65 | E6: =C6/$C$25 -> 0.029304269 | F6: =C6-D6 -> 115.58075 | G6: =IFERROR(F6/C6,0) -> 0.11924998
A7: Diagnostics | B7: =COUNTIF(ItemDetail.Confidential!$J:$J,A7) -> 2 | C7: =SUMIF(ItemDetail.Confidential!$J:$J,A7,ItemDetail.Confidential!$V:$V) -> 966.425 | D7: =SUMIF(ItemDetail.Confidential!$J:$J,A7,ItemDetail.Confidential!$R:$R) -> 835.2 | E7: =C7/$C$25 -> 0.029219438 | F7: =C7-D7 -> 131.225 | G7: =IFERROR(F7/C7,0) -> 0.13578395
A8: Facility Safety and Maintenance | B8: =COUNTIF(ItemDetail.Confidential!$J:$J,A8) -> 2 | C8: =SUMIF(ItemDetail.Confidential!$J:$J,A8,ItemDetail.Confidential!$V:$V) -> 169.49525 | D8: =SUMIF(ItemDetail.Confidential!$J:$J,A8,ItemDetail.Confidential!$R:$R) -> 177.71 | E8: =C8/$C$25 -> 0.0051246149 | F8: =C8-D8 -> -8.21475 | G8: =IFERROR(F8/C8,0) -> -0.04846596
A9: Filtration | B9: =COUNTIF(ItemDetail.Confidential!$J:$J,A9) -> 2 | C9: =SUMIF(ItemDetail.Confidential!$J:$J,A9,ItemDetail.Confidential!$V:$V) -> 286.165 | D9: =SUMIF(ItemDetail.Confidential!$J:$J,A9,ItemDetail.Confidential!$R:$R) -> 257.42 | E9: =C9/$C$25 -> 0.0086520738 | F9: =C9-D9 -> 28.745 | G9: =IFERROR(F9/C9,0) -> 0.10044904
A10: Glassware | B10: =COUNTIF(ItemDetail.Confidential!$J:$J,A10) -> 5 | C10: =SUMIF(ItemDetail.Confidential!$J:$J,A10,ItemDetail.Confidential!$V:$V) -> 1425.8908 | D10: =SUMIF(ItemDetail.Confidential!$J:$J,A10,ItemDetail.Confidential!$R:$R) -> 1323.16 | E10: =C10/$C$25 -> 0.043111184 | F10: =C10-D10 -> 102.73075 | G10: =IFERROR(F10/C10,0) -> 0.072046719
A11: Hotplates and Stirrers | B11: =COUNTIF(ItemDetail.Confidential!$J:$J,A11) -> 1 | C11: =SUMIF(ItemDetail.Confidential!$J:$J,A11,ItemDetail.Confidential!$V:$V) -> 632.9385 | D11: =SUMIF(ItemDetail.Confidential!$J:$J,A11,ItemDetail.Confidential!$R:$R) -> 599.64 | E11: =C11/$C$25 -> 0.019136619 | F11: =C11-D11 -> 33.2985 | G11: =IFERROR(F11/C11,0) -> 0.052609377
A12: Inorganic Chemicals | B12: =COUNTIF(ItemDetail.Confidential!$J:$J,A12) -> 4 | C12: =SUMIF(ItemDetail.Confidential!$J:$J,A12,ItemDetail.Confidential!$V:$V) -> 2483.379 | D12: =SUMIF(ItemDetail.Confidential!$J:$J,A12,ItemDetail.Confidential!$R:$R) -> 2158.643 | E12: =C12/$C$25 -> 0.07508388 | F12: =C12-D12 -> 324.736 | G12: =IFERROR(F12/C12,0) -> 0.13076377
A13: Lab Supplies | B13: =COUNTIF(ItemDetail.Confidential!$J:$J,A13) -> 11 | C13: =SUMIF(ItemDetail.Confidential!$J:$J,A13,ItemDetail.Confidential!$V:$V) -> 1071.8073 | D13: =SUMIF(ItemDetail.Confidential!$J:$J,A13,ItemDetail.Confidential!$R:$R) -> 883.87 | E13: =C13/$C$25 -> 0.032405624 | F13: =C13-D13 -> 187.93725 | G13: =IFERROR(F13/C13,0) -> 0.17534613
A14: Microbiology | B14: =COUNTIF(ItemDetail.Confidential!$J:$J,A14) -> 5 | C14: =SUMIF(ItemDetail.Confidential!$J:$J,A14,ItemDetail.Confidential!$V:$V) -> 1407.906 | D14: =SUMIF(ItemDetail.Confidential!$J:$J,A14,ItemDetail.Confidential!$R:$R) -> 1316.06 | E14: =C14/$C$25 -> 0.042567423 | F14: =C14-D14 -> 91.846 | G14: =IFERROR(F14/C14,0) -> 0.065235889
... A24: Sterilizers and Autoclaves | B24: =COUNTIF(ItemDetail.Confidential!$J:$J,A24) -> 1 | C24: =SUMIF(ItemDetail.Confidential!$J:$J,A24,ItemDetail.Confidential!$V:$V) -> 139.91125 | D24: =SUMIF(ItemDetail.Confidential!$J:$J,A24,ItemDetail.Confidential!$R:$R) -> 146.06 | E24: =C24/$C$25 -> 0.0042301556 | F24: =C24-D24 -> -6.14875 | G24: =IFERROR(F24/C24,0) -> -0.043947502
A25: Totals | B25: =SUM(B3:B24) -> 68 | C25: =SUM(C3:C24) -> 33074.729 | D25: =SUM(D3:D24) -> 27876.36 | E25: =SUM(E3:E24) -> 1 | F25: =SUM(F3:F24) -> 5198.3697 | G25: =F25/C25 -> 0.15717044

Sheet ItemDetail.Confidential
A3: CUSTOMER CITY | B3: ITEM NUMBER | C3: ITEM DESCRIPTION | D3: STANDARD UOM | E3: # OF UNITS IN A STND UOM | F3: Alternate UOM | G3: # OF SU UNITS IN AU | H3: MANUFACTURER NAME | I3: PRODUCT SEGMENT (CMT1) | J3: PRODUCT FAMILY (CMT2) | K3: MATERIAL CATEGORY (CMT3) | L3: PURCHASE AMOUNT | M3: TRANSACTIONS | N3: QTY PURCHASED | O3: LTM Savings $ | P3: LTM Savings % | Q3: LTM Savings Cat. | R3: PA Extended | S3: PA PRICE | T3: CSPL (Y/N) | U3: Pricing Category | V3: Current Extended | W3: Current Price | X3: Savings | Y3: Savings % | Z3: Savings Cat. | AA3: Category: Current Price or Average Price | AB3: List Price | AC3: List Extended | AD3: Discount off List | AE3: Discount % | AF3: Discount Category | AG3: Notes
A4: WISCASSET | B4: SS254200 | C4: SODIUM HYDROX SOL 50% CR 200L | D4: EA | E4: 1 | F4: EA | G4: 1 | H4: THERMO SCI FAIRLAWN CHEMICALS | I4: Chemicals | J4: Analytical Chemicals | K4: Caustics | L4: 4500 | M4: 1 | N4: 1 | O4: =L4-R4 -> 868.5 | P4: =O4/L4 -> 0.193 | Q4: =IF(P4<0,"Negative",IF(P4=0,"Same",IF(P4>0.3,"30+%",IF(P4>0.2,"20-30%",IF(P4>0.1,"10-20%",IF(P4<=0.1,"0-10%")))))) -> 10-20% | R4: =S4*N4 -> 3631.5 | S4: 3631.5 | T4: N | U4: Local Pricing | V4: =W4*N4 -> 4837.5 | W4: 4837.5 | X4: =V4-R4 -> 1206 | Y4: =X4/V4 -> 0.24930233 | Z4: =IF(Y4<0,"Negative",IF(Y4=0,"Same",IF(Y4>0.3,"30+%",IF(Y4>0.2,"20-30%",IF(Y4>0.1,"10-20%",IF(Y4<=0.1,"0-10%")))))) -> 20-30% | AA4: LTM AVG +7.5% | AB4: 4500 | AC4: =AB4*N4 -> 4500 | AD4: =AC4-R4 -> 868.5 | AE4: =AD4/AC4 -> 0.193 | AF4: =IF(AE4<0,"Negative",IF(AE4=0,"Same",IF(AE4>0.3,"30+%",IF(AE4>0.2,"20-30%",IF(AE4>0.1,"10-20%",IF(AE4<=0.1,"0-10%")))))) -> 10-20%
A5: WISCASSET | B5: A200C212 | C5: NITRIC ACID R ACS 4X21/2L/CS | D5: CS | E5: 4 | F5: CS | G5: 1 | H5: THERMO SCI FAIRLAWN CHEMICALS | I5: Chemicals | J5: Analytical Chemicals | K5: Acids | L5: 3363.82 | M5: 10 | N5: 16 | O5: =L5-R5 -> 168.191 | P5: =O5/L5 -> 0.05 | Q5: =IF(P5<0,"Negative",IF(P5=0,"Same",IF(P5>0.3,"30+%",IF(P5>0.2,"20-30%",IF(P5>0.1,"10-20%",IF(P5<=0.1,"0-10%")))))) -> 0-10% | R5: =S5*N5 -> 3195.629 | S5: 199.72681 | T5: N | U5: Local Pricing | V5: =W5*N5 -> 3616.1065 | W5: 226.00666 | X5: =V5-R5 -> 420.4775 | Y5: =X5/V5 -> 0.11627907 | Z5: =IF(Y5<0,"Negative",IF(Y5=0,"Same",IF(Y5>0.3,"30+%",IF(Y5>0.2,"20-30%",IF(Y5>0.1,"10-20%",IF(Y5<=0.1,"0-10%")))))) -> 10-20% | AA5: LTM AVG +7.5% | AB5: 416 | AC5: =AB5*N5 -> 6656 | AD5: =AC5-R5 -> 3460.371 | AE5: =AD5/AC5 -> 0.51988747 | AF5: =IF(AE5<0,"Negative",IF(AE5=0,"Same",IF(AE5>0.3,"30+%",IF(AE5>0.2,"20-30%",IF(AE5>0.1,"10-20%",IF(AE5<=0.1,"0-10%")))))) -> 30+%
A6: WISCASSET | B6: 305832 | C6: FERRIC AMM SULFATE TS, 1L | D6: EA | E6: 1 | F6: EA | G6: 1 | H6: RICCA CHEMICAL | I6: Chemicals | J6: Solutions and Standard Chemicals | K6: Solution[s] for Chemical Testing | L6: 3286.4 | M6: 5 | N6: 26 | O6: =L6-R6 -> 164.32 | P6: =O6/L6 -> 0.05 | Q6: =IF(P6<0,"Negative",IF(P6=0,"Same",IF(P6>0.3,"30+%",IF(P6>0.2,"20-30%",IF(P6>0.1,"10-20%",IF(P6<=0.1,"0-10%")))))) -> 0-10% | R6: =S6*N6 -> 3122.08 | S6: 120.08 | T6: N | U6: Local Pricing | V6: =W6*N6 -> 3532.88 | W6: 135.88 | X6: =V6-R6 -> 410.8 | Y6: =X6/V6 -> 0.11627907 | Z6: =IF(Y6<0,"Negative",IF(Y6=0,"Same",IF(Y6>0.3,"30+%",IF(Y6>0.2,"20-30%",IF(Y6>0.1,"10-20%",IF(Y6<=0.1,"0-10%")))))) -> 10-20% | AA6: LTM AVG +7.5% | AB6: 185.81 | AC6: =AB6*N6 -> 4831.06 | AD6: =AC6-R6 -> 1708.98 | AE6: =AD6/AC6 -> 0.35374845 | AF6: =IF(AE6<0,"Negative",IF(AE6=0,"Same",IF(AE6>0.3,"30+%",IF(AE6>0.2,"20-30%",IF(AE6>0.1,"10-20%",IF(AE6<=0.1,"0-10%")))))) -> 30+%
A7: WISCASSET | B7: ST181 | C7: THIOCYANATE STD N/10 CERT 1L | D7: EA | E7: 1 | F7: CS | G7: 6 | H7: THERMO SCI FAIRLAWN CHEMICALS | I7: Chemicals | J7: Solutions and Standard Chemicals | K7: Standards | L7: 1927.19 | M7: 6 | N7: 34 | O7: =L7-R7 -> 96.3595 | P7: =O7/L7 -> 0.05 | Q7: =IF(P7<0,"Negative",IF(P7=0,"Same",IF(P7>0.3,"30+%",IF(P7>0.2,"20-30%",IF(P7>0.1,"10-20%",IF(P7<=0.1,"0-10%")))))) -> 0-10% | R7: =S7*N7 -> 1830.8305 | S7: 53.847956 | T7: N | U7: Local Pricing | V7: =W7*N7 -> 2071.7292 | W7: 60.933213 | X7: =V7-R7 -> 240.89875 | Y7: =X7/V7 -> 0.11627907 | Z7: =IF(Y7<0,"Negative",IF(Y7=0,"Same",IF(Y7>0.3,"30+%",IF(Y7>0.2,"20-30%",IF(Y7>0.1,"10-20%",IF(Y7<=0.1,"0-10%")))))) -> 10-20% | AA7: LTM AVG +7.5% | AB7: 118 | AC7: =AB7*N7 -> 4012 | AD7: =AC7-R7 -> 2181.1695 | AE7: =AD7/AC7 -> 0.54366139 | AF7: =IF(AE7<0,"Negative",IF(AE7=0,"Same",IF(AE7>0.3,"30+%",IF(AE7>0.2,"20-30%",IF(AE7>0.1,"10-20%",IF(AE7<=0.1,"0-10%")))))) -> 30+%
A8: WISCASSET | B8: SS25420 | C8: SODIUM HYDROX SOL 50% CR 20L | D8: EA | E8: 1 | F8: EA | G8: 1 | H8: THERMO SCI FAIRLAWN CHEMICALS | I8: Chemicals | J8: Analytical Chemicals | K8: Caustics | L8: 1863.48 | M8: 2 | N8: 6 | O8: =L8-R8 -> 93.174 | P8: =O8/L8 -> 0.05 | Q8: =IF(P8<0,"Negative",IF(P8=0,"Same",IF(P8>0.3,"30+%",IF(P8>0.2,"20-30%",IF(P8>0.1,"10-20%",IF(P8<=0.1,"0-10%")))))) -> 0-10% | R8: =S8*N8 -> 1770.306 | S8: 295.051 | T8: N | U8: Local Pricing | V8: =W8*N8 -> 2003.241 | W8: 333.8735 | X8: =V8-R8 -> 232.935 | Y8: =X8/V8 -> 0.11627907 | Z8: =IF(Y8<0,"Negative",IF(Y8=0,"Same",IF(Y8>0.3,"30+%",IF(Y8>0.2,"20-30%",IF(Y8>0.1,"10-20%",IF(Y8<=0.1,"0-10%")))))) -> 10-20% | AA8: LTM AVG +7.5% | AB8: 1192.5 | AC8: =AB8*N8 -> 7155 | AD8: =AC8-R8 -> 5384.694 | AE8: =AD8/AC8 -> 0.75257778 | AF8: =IF(AE8<0,"Negative",IF(AE8=0,"Same",IF(AE8>0.3,"30+%",IF(AE8>0.2,"20-30%",IF(AE8>0.1,"10-20%",IF(AE8<=0.1,"0-10%")))))) -> 30+%
A9: BRUNSWICK | B9: 13683553 | C9: REPEATER E3X W/ CHARGING STAND | D9: EA | E9: 1 | F9: EA | G9: 1 | H9: EPPENDORF NORTH AMERICA BIOTOOLS | I9: Glass, Plastic, and Liquid Handling | J9: Pipetters and Dispensers | K9: Single Channel Pipetters | L9: 1589.18 | M9: 1 | N9: 1 | O9: =L9-R9 -> -72.52 | P9: =O9/L9 -> -0.045633597 | Q9: =IF(P9<0,"Negative",IF(P9=0,"Same",IF(P9>0.3,"30+%",IF(P9>0.2,"20-30%",IF(P9>0.1,"10-20%",IF(P9<=0.1,"0-10%")))))) -> Negative | R9: =S9*N9 -> 1661.7 | S9: 1661.7 | T9: N | U9: PPG Pricing | V9: =W9*N9 -> 1708.3685 | W9: 1708.3685 | X9: =V9-R9 -> 46.6685 | Y9: =X9/V9 -> 0.027317584 | Z9: =IF(Y9<0,"Negative",IF(Y9=0,"Same",IF(Y9>0.3,"30+%",IF(Y9>0.2,"20-30%",IF(Y9>0.1,"10-20%",IF(Y9<=0.1,"0-10%")))))) -> 0-10% | AA9: LTM AVG +7.5% | AB9: 1751 | AC9: =AB9*N9 -> 1751 | AD9: =AC9-R9 -> 89.3 | AE9: =AD9/AC9 -> 0.050999429 | AF9: =IF(AE9<0,"Negative",IF(AE9=0,"Same",IF(AE9>0.3,"30+%",IF(AE9>0.2,"20-30%",IF(AE9>0.1,"10-20%",IF(AE9<=0.1,"0-10%")))))) -> 0-10%
A10: WISCASSET | B10: S42150 | C10: SODIUM SULFATE CERT ACS 50KG | D10: EA | E10: 1 | F10: EA | G10: 1 | H10: THERMO SCI FAIRLAWN CHEMICALS | I10: Chemicals | J10: Inorganic Chemicals | K10: Sodium Inorganic Compounds | L10: 942.72 | M10: 1 | N10: 1 | O10: =L10-R10 -> 47.136 | P10: =O10/L10 -> 0.05 | Q10: =IF(P10<0,"Negative",IF(P10=0,"Same",IF(P10>0.3,"30+%",IF(P10>0.2,"20-30%",IF(P10>0.1,"10-20%",IF(P10<=0.1,"0-10%")))))) -> 0-10% | R10: =S10*N10 -> 895.584 | S10: 895.584 | T10: N | U10: Local Pricing | V10: =W10*N10 -> 1013.424 | W10: 1013.424 | X10: =V10-R10 -> 117.84 | Y10: =X10/V10 -> 0.11627907 | Z10: =IF(Y10<0,"Negative",IF(Y10=0,"Same",IF(Y10>0.3,"30+%",IF(Y10>0.2,"20-30%",IF(Y10>0.1,"10-20%",IF(Y10<=0.1,"0-10%")))))) -> 10-20% | AA10: LTM AVG +7.5% | AB10: 2400 | AC10: =AB10*N10 -> 2400 | AD10: =AC10-R10 -> 1504.416 | AE10: =AD10/AC10 -> 0.62684 | AF10: =IF(AE10<0,"Negative",IF(AE10=0,"Same",IF(AE10>0.3,"30+%",IF(AE10>0.2,"20-30%",IF(AE10>0.1,"10-20%",IF(AE10<=0.1,"0-10%")))))) -> 30+%
A11: WISCASSET | B11: FB02912025A | C11: JAR 1OZ PP NAT UNLINED 72/CS | D11: CS | E11: 72 | F11: CS | G11: 1 | H11: DWK LIFE SCIENCES LLC | I11: Glass, Plastic, and Liquid Handling | J11: Other Plasticware | K11: Plastic Jugs and Jars | L11: 915.39 | M11: 5 | N11: 9 | O11: =L11-R11 -> 18.81 | P11: =O11/L11 -> 0.020548619 | Q11: =IF(P11<0,"Negative",IF(P11=0,"Same",IF(P11>0.3,"30+%",IF(P11>0.2,"20-30%",IF(P11>0.1,"10-20%",IF(P11<=0.1,"0-10%")))))) -> 0-10% | R11: =S11*N11 -> 896.58 | S11: 99.62 | T11: N | U11: PPG Pricing | V11: =W11*N11 -> 984.04425 | W11: 109.33825 | X11: =V11-R11 -> 87.46425 | Y11: =X11/V11 -> 0.088882436 | Z11: =IF(Y11<0,"Negative",IF(Y11=0,"Same",IF(Y11>0.3,"30+%",IF(Y11>0.2,"20-30%",IF(Y11>0.1,"10-20%",IF(Y11<=0.1,"0-10%")))))) -> 0-10% | AA11: LTM AVG +7.5% | AB11: 114.5 | AC11: =AB11*N11 -> 1030.5 | AD11: =AC11-R11 -> 133.92 | AE11: =AD11/AC11 -> 0.12995633 | AF11: =IF(AE11<0,"Negative",IF(AE11=0,"Same",IF(AE11>0.3,"30+%",IF(AE11>0.2,"20-30%",IF(AE11>0.1,"10-20%",IF(AE11<=0.1,"0-10%")))))) -> 10-20%
A12: BRUNSWICK | B12: H3604 | C12: N-HEPTANE, OPTIMA 4L | D12: EA | E12: 1 | F12: CS | G12: 4 | H12: THERMO SCI FAIRLAWN CHEMICALS | I12: Chemicals | J12: Solvents | K12: Heptane [n-] | L12: 844.56 | M12: 2 | N12: 5 | O12: =L12-R12 -> 275.91 | P12: =O12/L12 -> 0.32669082 | Q12: =IF(P12<0,"Negative",IF(P12=0,"Same",IF(P12>0.3,"30+%",IF(P12>0.2,"20-30%",IF(P12>0.1,"10-20%",IF(P12<=0.1,"0-10%")))))) -> 30+% | R12: =S12*N12 -> 568.65 | S12: 113.73 | T12: N | U12: Rebate | V12: =W12*N12 -> 907.902 | W12: 181.5804 | X12: =V12-R12 -> 339.252 | Y12: =X12/V12 -> 0.37366588 | Z12: =IF(Y12<0,"Negative",IF(Y12=0,"Same",IF(Y12>0.3,"30+%",IF(Y12>0.2,"20-30%",IF(Y12>0.1,"10-20%",IF(Y12<=0.1,"0-10%")))))) -> 30+% | AA12: LTM AVG +7.5% | AB12: 461.5 | AC12: =AB12*N12 -> 2307.5 | AD12: =AC12-R12 -> 1738.85 | AE12: =AD12/AC12 -> 0.75356446 | AF12: =IF(AE12<0,"Negative",IF(AE12=0,"Same",IF(AE12>0.3,"30+%",IF(AE12>0.2,"20-30%",IF(AE12>0.1,"10-20%",IF(AE12<=0.1,"0-10%")))))) -> 30+%
A13: WISCASSET | B13: S41550 | C13: SOD SULFT ACS AN 10/60M 50KG | D13: EA | E13: 1 | F13: EA | G13: 1 | H13: THERMO SCI FAIRLAWN CHEMICALS | I13: Chemicals | J13: Inorganic Chemicals | K13: Sodium Inorganic Compounds | L13: 762.22 | M13: 1 | N13: 1 | O13: =L13-R13 -> 38.111 | P13: =O13/L13 -> 0.05 | Q13: =IF(P13<0,"Negative",IF(P13=0,"Same",IF(P13>0.3,"30+%",IF(P13>0.2,"20-30%",IF(P13>0.1,"10-20%",IF(P13<=0.1,"0-10%")))))) -> 0-10% | R13: =S13*N13 -> 724.109 | S13: 724.109 | T13: N | U13: Local Pricing | V13: =W13*N13 -> 819.3865 | W13: 819.3865 | X13: =V13-R13 -> 95.2775 | Y13: =X13/V13 -> 0.11627907 | Z13: =IF(Y13<0,"Negative",IF(Y13=0,"Same",IF(Y13>0.3,"30+%",IF(Y13>0.2,"20-30%",IF(Y13>0.1,"10-20%",IF(Y13<=0.1,"0-10%")))))) -> 10-20% | AA13: LTM AVG +7.5% | AB13: 1388 | AC13: =AB13*N13 -> 1388 | AD13: =AC13-R13 -> 663.891 | AE13: =AD13/AC13 -> 0.47830764 | AF13: =IF(AE13<0,"Negative",IF(AE13=0,"Same",IF(AE13>0.3,"30+%",IF(AE13>0.2,"20-30%",IF(AE13>0.1,"10-20%",IF(AE13<=0.1,"0-10%")))))) -> 30+%
A14: WISCASSET | B14: A41620 | C14: 2-PROPANOL CERTIFIED ACS 20L | D14: EA | E14: 1 | F14: EA | G14: 1 | H14: THERMO SCI FAIRLAWN CHEMICALS | I14: Chemicals | J14: Solvents | K14: Isopropanol [IPA] | L14: 682.92 | M14: 2 | N14: 3 | O14: =L14-R14 -> 165.57 | P14: =O14/L14 -> 0.24244421 | Q14: =IF(P14<0,"Negative",IF(P14=0,"Same",IF(P14>0.3,"30+%",IF(P14>0.2,"20-30%",IF(P14>0.1,"10-20%",IF(P14<=0.1,"0-10%")))))) -> 20-30% | R14: =S14*N14 -> 517.35 | S14: 172.45 | T14: Y | U14: Current Hotlist | V14: =W14*N14 -> 734.139 | W14: 244.713 | X14: =V14-R14 -> 216.789 | Y14: =X14/V14 -> 0.29529694 | Z14: =IF(Y14<0,"Negative",IF(Y14=0,"Same",IF(Y14>0.3,"30+%",IF(Y14>0.2,"20-30%",IF(Y14>0.1,"10-20%",IF(Y14<=0.1,"0-10%")))))) -> 20-30% | AA14: LTM AVG +7.5% | AB14: 646.5 | AC14: =AB14*N14 -> 1939.5 | AD14: =AC14-R14 -> 1422.15 | AE14: =AD14/AC14 -> 0.73325599 | AF14: =IF(AE14<0,"Negative",IF(AE14=0,"Same",IF(AE14>0.3,"30+%",IF(AE14>0.2,"20-30%",IF(AE14>0.1,"10-20%",IF(AE14<=0.1,"0-10%")))))) -> 30+%
A15: WISCASSET | B15: S07977S | C15: RT BASIC STIRRER SM 120V | D15: EA | E15: 1 | F15: EA | G15: 1 | H15: THERMO SCI ASHEVILLE | I15: Lab Appliances | J15: Hotplates and Stirrers | K15: Stirrers | L15: 588.78 | M15: 2 | N15: 3 | O15: =L15-R15 -> -10.86 | P15: =O15/L15 -> -0.01844492 | Q15: =IF(P15<0,"Negative",IF(P15=0,"Same",IF(P15>0.3,"30+%",IF(P15>0.2,"20-30%",IF(P15>0.1,"10-20%",IF(P15<=0.1,"0-10%")))))) -> Negative | R15: =S15*N15 -> 599.64 | S15: 199.88 | T15: N | U15: PPG Pricing | V15: =W15*N15 -> 632.9385 | W15: 210.9795 | X15: =V15-R15 -> 33.2985 | Y15: =X15/V15 -> 0.052609377 | Z15: =IF(Y15<0,"Negative",IF(Y15=0,"Same",IF(Y15>0.3,"30+%",IF(Y15>0.2,"20-30%",IF(Y15>0.1,"10-20%",IF(Y15<=0.1,"0-10%")))))) -> 0-10% | AA15: LTM AVG +7.5% | AB15: 205 | AC15: =AB15*N15 -> 615 | AD15: =AC15-R15 -> 15.36 | AE15: =AD15/AC15 -> 0.02497561 | AF15: =IF(AE15<0,"Negative",IF(AE15=0,"Same",IF(AE15>0.3,"30+%",IF(AE15>0.2,"20-30%",IF(AE15>0.1,"10-20%",IF(AE15<=0.1,"0-10%")))))) -> 0-10%
... A71: WISCASSET | B71: 06666A | C71: KIMWIPE SML 4-1/2X8-1/2 280/PK | D71: PK | E71: 280 | F71: CS | G71: 60 | H71: KIMBERLY CLARK AWAY FROM HOME DIVISION | I71: Safety | J71: Facility Safety and Maintenance | K71: Facility Maintenance | L71: 0 | M71: 1 | N71: 3 | O71: =L71-R71 -> -13.29 | P71: =O71/L71 -> #DIV/0! | Q71: =IF(P71<0,"Negative",IF(P71=0,"Same",IF(P71>0.3,"30+%",IF(P71>0.2,"20-30%",IF(P71>0.1,"10-20%",IF(P71<=0.1,"0-10%")))))) -> #DIV/0! | R71: =S71*N71 -> 13.29 | S71: 4.43 | T71: Y | U71: Current Hotlist | V71: =W71*N71 -> 0 | W71: 0 | X71: =V71-R71 -> -13.29 | Y71: =X71/V71 -> #DIV/0! | Z71: =IF(Y71<0,"Negative",IF(Y71=0,"Same",IF(Y71>0.3,"30+%",IF(Y71>0.2,"20-30%",IF(Y71>0.1,"10-20%",IF(Y71<=0.1,"0-10%")))))) -> #DIV/0! | AA71: LTM AVG +7.5% | AB71: 12.22 | AC71: =AB71*N71 -> 36.66 | AD71: =AC71-R71 -> 23.37 | AE71: =AD71/AC71 -> 0.63747954 | AF71: =IF(AE71<0,"Negative",IF(AE71=0,"Same",IF(AE71>0.3,"30+%",IF(AE71>0.2,"20-30%",IF(AE71>0.1,"10-20%",IF(AE71<=0.1,"0-10%")))))) -> 30+%

Sheet Excluded.Confidential
A1: CUSTOMER CITY | B1: ITEM NUMBER | C1: ITEM DESCRIPTION | D1: STANDARD UOM | E1: # OF UNITS IN A STND UOM | F1: Alternate UOM | G1: # OF SU UNITS IN AU | H1: MANUFACTURER NAME | I1: PRODUCT SEGMENT (CMT1) | J1: PRODUCT FAMILY (CMT2) | K1: MATERIAL CATEGORY (CMT3) | L1: PURCHASE AMOUNT | M1: TRANSACTIONS | N1: QTY PURCHASED | O1: CSPL | P1: Notes
